QELMChatUI.py
QelmT.py
qelm/__init__.py
qelm-0.1.4.dist-info/licenses/LICENSE
qelm-0.1.4.dist-info/METADATA
qelm-0.1.4.dist-info/WHEEL
qelm-0.1.4.dist-info/top_level.txt
qelm-0.1.4.dist-info/RECORD
