Metadata-Version: 2.4
Name: qelm
Version: 0.1.4
Summary: Quantum-Enhanced Language Model
Author: Brenton Carter
License-Expression: MIT
Requires-Python: >=3.9
License-File: LICENSE
Requires-Dist: qiskit-aer>=0.12
Requires-Dist: qiskit>=1.0
Requires-Dist: tensorflow>=2.16
Requires-Dist: nltk>=3.8
Requires-Dist: psutil>=5.9
Requires-Dist: matplotlib>=3.8
Dynamic: license-file
